[
  {
    "id": "222",
    "url": "http://1300489241.vod2.myqcloud.com/8d88edc2vodcq1300489241/846478855285890794138800102/FUS5cpKBqdMA.mp4",
    "userAvatar": "https://raw.githubusercontent.com/tuke0919/xiaoshujiang_image/master/xiaoshujiang/08A06CADDC42CE8A79D219B770B37819.jpg",
    "isWatched": true,
    "voteCount": 13223,
    "commentCount": 47788,
    "shareCount": 322,
    "userName": "惠闵",
    "description": "所以...以后该叫我什么？@抖音小助手",
    "music": "@惠闵创作的原声-惠闵",
    "musicImage": "",
    "createTime": 1571669432000
  },
  {
    "id": "3232",
    "url": "http://1300489241.vod2.myqcloud.com/8d88edc2vodcq1300489241/bf4828905285890795108641139/T0daAYpodbcA.mp4",
    "userAvatar": "https://raw.githubusercontent.com/tuke0919/xiaoshujiang_image/master/xiaoshujiang/B2275D129EEB34BE3B9CC8493249C8E5.jpg",
    "isWatched": true,
    "voteCount": 44214,
    "commentCount": 88797,
    "shareCount": 3222,
    "userName": "聚明星电器",
    "description": "昨天有个朋友说高速上油门卡住了幸好车流少，再发一次库存，希望更多的朋友看到，@抖音小助手",
    "music": "@聚明星电器创作的原声-聚明星电器",
    "musicImage": "",
    "createTime": 1571669432000
  },
  {
    "id": "7667",
    "url": "http://1300489241.vod2.myqcloud.com/8d88edc2vodcq1300489241/403e07da5285890794134118998/64nzq9AusDQA.mp4",
    "userAvatar": "https://raw.githubusercontent.com/tuke0919/xiaoshujiang_image/master/xiaoshujiang/51B8D4997618E5CC8AE69D43B13D995C.jpg",
    "isWatched": true,
    "voteCount": 23322,
    "commentCount": 667556,
    "shareCount": 87788,
    "userName": "哈士晴",
    "description": "我妈今天让我去相亲，说女孩子一定要表演才艺才能吸引有吸引优秀的男孩子，你们看我的才艺行吗？@抖音小助手",
    "music": "网易_大田后生仔-抖音神曲音乐汇",
    "musicImage": "",
    "createTime": 15716634234000
  },
  {
    "id": "23232",
    "url": "http://1300489241.vod2.myqcloud.com/8d88edc2vodcq1300489241/6693c2ac5285890795107134643/pUzX1Z5ksK0A.mp4",
    "userAvatar": "https://raw.githubusercontent.com/tuke0919/xiaoshujiang_image/master/xiaoshujiang/86C5D08AB323FF3DC6808C55F1DF6BD4.jpg",
    "isWatched": true,
    "voteCount": 9889,
    "commentCount": 66473,
    "shareCount": 22312,
    "userName": "我是面条",
    "description": "婴语，奶奶肯定没听懂，洗着洗着就不乐意了呢！委屈巴巴的，这表情太可爱了。",
    "music": "@我是面条创作的原声-我是面条",
    "musicImage": "",
    "createTime": 15716634234000
  },
  {
    "id": "5445",
    "url": "http://1300489241.vod2.myqcloud.com/8d88edc2vodcq1300489241/b128eb2d5285890795108028515/E4wnt2Mk788A.mp4",
    "userAvatar": "https://raw.githubusercontent.com/tuke0919/xiaoshujiang_image/master/xiaoshujiang/10F446580E2DE05429CA5ED384D8E2C4.jpg",
    "isWatched": true,
    "voteCount": 433322,
    "commentCount": 122322,
    "shareCount": 56442,
    "userName": "芙蓉",
    "description": "玉龙雪山，遗憾没有看到雪。",
    "music": "@哈尔滨工程大学创作的原声-哈尔滨工程大学",
    "musicImage": "",
    "createTime": 15716634234000
  },
  {
    "id": "99888",
    "url": "http://1300489241.vod2.myqcloud.com/8d88edc2vodcq1300489241/6693c2ac5285890795107134643/pUzX1Z5ksK0A.mp4",
    "userAvatar": "https://raw.githubusercontent.com/tuke0919/xiaoshujiang_image/master/xiaoshujiang/41F94846CCF6EE88181C672F2E9D677A.jpg",
    "isWatched": true,
    "voteCount": 433256,
    "commentCount": 8778,
    "shareCount": 98986,
    "userName": "全球音乐榜",
    "description": "音乐这东西，开心时入耳，伤心时入心。#情感 #音乐@抖音小助手",
    "music": "@全球音乐榜创作的原声-全球音乐榜",
    "musicImage": "",
    "createTime": 15713634434000
  },
  {
    "id": "23422",
    "url": "http://1300489241.vod2.myqcloud.com/8d88edc2vodcq1300489241/6694c62e5285890795107136148/PJgxiky4GcIA.mp4",
    "userAvatar": "https://raw.githubusercontent.com/tuke0919/xiaoshujiang_image/master/xiaoshujiang/6EEEF83C6C293FC02103BFB3C2573AEE.jpg",
    "isWatched": true,
    "voteCount": 76674,
    "commentCount": 3224,
    "shareCount": 98898,
    "userName": "老街电台",
    "description": "#吴奇隆 18岁时#刘诗诗 才1岁，所以说没有该结婚的年龄，再晚也要等到爱的人。#爱情 #终于等到你",
    "music": "@全球音乐榜创作的原声-全球音乐榜",
    "musicImage": "",
    "createTime": 15713634431000
  },
  {
    "id": "8778",
    "url": "http://1300489241.vod2.myqcloud.com/8d88edc2vodcq1300489241/901b132b5285890795104850154/Naied832Ua0A.mp4",
    "userAvatar": "https://raw.githubusercontent.com/tuke0919/xiaoshujiang_image/master/xiaoshujiang/86C5D08AB323FF3DC6808C55F1DF6BD4.jpg",
    "isWatched": true,
    "voteCount": 67652,
    "commentCount": 1233,
    "shareCount": 8897,
    "userName": "四川大学",
    "description": "#我的校园 暮色江安，光影里是不是有你的憧憬与回忆？@抖音校园 @西瓜",
    "music": "@四川大学创作的原声-四川大学",
    "musicImage": "",
    "createTime": 15713634431000
  },
  {
    "id": "2333",
    "url": "http://1300489241.vod2.myqcloud.com/8d88edc2vodcq1300489241/21046d4d5285890795106492341/twe1SrK5lDwA.mp4",
    "userAvatar": "https://raw.githubusercontent.com/tuke0919/xiaoshujiang_image/master/xiaoshujiang/96DC74BDF7AE496C6FDC7906C70EB0D5.jpg",
    "isWatched": true,
    "voteCount": 6554,
    "commentCount": 23277,
    "shareCount": 96643,
    "userName": "旅途十万里",
    "description": "在最好的年纪，做最疯狂的事",
    "music": "@旅途十万里创作的原声-旅途十万里",
    "musicImage": "",
    "createTime": 15713630431000
  },
  {
    "id": "6555",
    "url": "http://1300489241.vod2.myqcloud.com/8d88edc2vodcq1300489241/faae0e2a5285890795062126226/x6gAqGTUXfoA.mp4",
    "userAvatar": "https://raw.githubusercontent.com/tuke0919/xiaoshujiang_image/master/xiaoshujiang/86C5D08AB323FF3DC6808C55F1DF6BD4.jpg",
    "isWatched": true,
    "voteCount": 4445,
    "commentCount": 75455,
    "shareCount": 90884,
    "userName": "婷婷",
    "description": "这才是秋天该有的样子，真是太美了#旅行 #秋天该有的样子",
    "music": "@鱼大仙儿（文弘音乐）创作的原声-鱼大仙儿（文弘音乐）",
    "musicImage": "",
    "createTime": 15711634431000
  }
]